odoo/addons/survey_formio/README.rst
odoo/addons/survey_formio/__init__.py
odoo/addons/survey_formio/__manifest__.py
odoo/addons/survey_formio/i18n/it.po
odoo/addons/survey_formio/i18n/survey_formio.pot
odoo/addons/survey_formio/models/__init__.py
odoo/addons/survey_formio/models/survey.py
odoo/addons/survey_formio/models/survey_question.py
odoo/addons/survey_formio/readme/CONTRIBUTORS.rst
odoo/addons/survey_formio/readme/DESCRIPTION.rst
odoo/addons/survey_formio/readme/ROADMAP.rst
odoo/addons/survey_formio/readme/USAGE.rst
odoo/addons/survey_formio/static/description/icon.png
odoo/addons/survey_formio/static/description/index.html
odoo/addons/survey_formio/tests/__init__.py
odoo/addons/survey_formio/tests/test_survey_formio.py
odoo_addon_survey_formio-16.0.1.0.0.1.dist-info/METADATA
odoo_addon_survey_formio-16.0.1.0.0.1.dist-info/WHEEL
odoo_addon_survey_formio-16.0.1.0.0.1.dist-info/top_level.txt
odoo_addon_survey_formio-16.0.1.0.0.1.dist-info/RECORD
