Metadata-Version: 2.1
Name: odoo-addon-survey_formio
Version: 16.0.1.0.0.1
Summary: This module allows the generation of a form.io compatible JSON for a survey.
Home-page: https://github.com/OCA/survey
Author: Odoo Community Association (OCA), ACSONE SA/NV
Author-email: support@odoo-community.org
License: AGPL-3
Classifier: Programming Language :: Python
Classifier: Framework :: Odoo
Classifier: Framework :: Odoo :: 16.0
Classifier: License :: OSI Approved :: GNU Affero General Public License v3
Requires-Python: >=3.10
Requires-Dist: odoo<16.1dev,>=16.0a
